oldpy2store/__init__.py
oldpy2store-0.0.4.dist-info/LICENSE
oldpy2store-0.0.4.dist-info/LICENSE.txt
oldpy2store-0.0.4.dist-info/METADATA
oldpy2store-0.0.4.dist-info/WHEEL
oldpy2store-0.0.4.dist-info/top_level.txt
oldpy2store-0.0.4.dist-info/RECORD
