Metadata-Version: 2.1
Name: oldpy2store
Version: 0.0.4
Summary: Old version of py2store
Home-page: https://github.com/thorwhalen/oldpy2store
Author: Thor Whalen
License: apache-2.0
Platform: any
